configkit/__init__.py
configkit/configkit.py
configkit/py.typed
pyconfigkit-1.0.0.dist-info/licenses/LICENSE
pyconfigkit-1.0.0.dist-info/METADATA
pyconfigkit-1.0.0.dist-info/WHEEL
pyconfigkit-1.0.0.dist-info/top_level.txt
pyconfigkit-1.0.0.dist-info/RECORD
