Metadata-Version: 2.4
Name: pyConfigKit
Version: 1.0.0
Summary: Thread-safe singleton JSON configuration loader with JSON Schema validation
Author: Miichoow
License-Expression: MIT
Project-URL: Homepage, https://github.com/miichoow/ConfigKit
Project-URL: Repository, https://github.com/miichoow/ConfigKit
Project-URL: Issues, https://github.com/miichoow/ConfigKit/issues
Keywords: configuration,json,schema,validation,singleton,config
Classifier: Development Status :: 5 - Production/Stable
Classifier: Intended Audience :: Developers
Classifier: Operating System :: OS Independent
Classifier: Programming Language :: Python :: 3
Classifier: Programming Language :: Python :: 3.9
Classifier: Programming Language :: Python :: 3.10
Classifier: Programming Language :: Python :: 3.11
Classifier: Programming Language :: Python :: 3.12
Classifier: Programming Language :: Python :: 3.13
Classifier: Topic :: Software Development :: Libraries :: Python Modules
Classifier: Typing :: Typed
Requires-Python: >=3.9
License-File: LICENSE
Requires-Dist: jsonschema>=4.21.0
Provides-Extra: dev
Requires-Dist: ruff>=0.4.0; extra == "dev"
Requires-Dist: mypy>=1.10.0; extra == "dev"
Requires-Dist: build>=1.0.0; extra == "dev"
Requires-Dist: twine>=5.0.0; extra == "dev"
Dynamic: license-file
